gitops/__init__.py
gitops/core.py
gitops/main.py
gitops/py.typed
gitops/settings.py
gitops/shorthands.py
gitops/common/__init__.py
gitops/common/app.py
gitops/common/utils.py
gitops/utils/__init__.py
gitops/utils/apps.py
gitops/utils/async_runner.py
gitops/utils/cli.py
gitops/utils/exceptions.py
gitops/utils/images.py
gitops/utils/kube.py
gitops/utils/tags.py
gitops/utils/yaml.py
gitops-1.5.1.dist-info/METADATA
gitops-1.5.1.dist-info/WHEEL
gitops-1.5.1.dist-info/entry_points.txt
gitops-1.5.1.dist-info/licenses/LICENSE
gitops-1.5.1.dist-info/RECORD
