Metadata-Version: 2.4
Name: gitops
Version: 1.5.1
Summary: Manage multiple apps across one or more k8s clusters.
Author-email: Jarek Głowacki <jarekwg@gmail.com>
License-File: LICENSE
Requires-Python: >=3.12
Requires-Dist: boto3>=1.35.4
Requires-Dist: colorama>=0.4.4
Requires-Dist: dsnparse==0.2.1
Requires-Dist: humanize>=3.5.0
Requires-Dist: invoke>=2.2.0
Requires-Dist: packaging>=24.1
Requires-Dist: pyyaml>=6.0.2
Requires-Dist: tabulate>=0.8.9
Provides-Extra: server
Requires-Dist: fastapi==0.109.2; extra == 'server'
Requires-Dist: httpx<0.24.0,>=0.23.0; extra == 'server'
Requires-Dist: kubernetes-asyncio>=25.1.2; extra == 'server'
Requires-Dist: sentry-sdk>=1.3.0; extra == 'server'
Requires-Dist: slack-sdk>=3.33.5; extra == 'server'
Requires-Dist: uptick-observability[fastapi]>=0.2.2; extra == 'server'
Requires-Dist: uvicorn>=0.34.0; extra == 'server'
